<templateSet group="Python">
  <template name="pdb" value="import pdb; pdb.set_trace()" description="import pdb" toReformat="false" toShortenFQNames="true">
    <context>
      <option name="Python" value="true" />
    </context>
  </template>
  <template name="write_fun" value="import codecs&#10;with codecs.open('tr.html', 'w', 'utf-8') as f:&#10;  f.write(html)" description="write to file" toReformat="true" toShortenFQNames="true">
    <context>
      <option name="Python" value="true" />
    </context>
  </template>
  <template name="ipdb" value="import ipdb; ipdb.set_trace()" description="ipdb" toReformat="false" toShortenFQNames="true">
    <context>
      <option name="Python" value="true" />
    </context>
  </template>
  <template name="called_by" value="import inspect&#10;print 'caller name:', inspect.stack()[1][3]" toReformat="false" toShortenFQNames="true">
    <context>
      <option name="Python" value="true" />
    </context>
  </template>
</templateSet>